imgreg/__init__.py
imgreg/data/__init__.py
imgreg/data/mod_img.jpg
imgreg/data/ref_img.jpg
imgreg/models/__init__.py
imgreg/models/angleselect/__init__.py
imgreg/models/angleselect/enums.py
imgreg/models/angleselect/params.py
imgreg/models/angleselect/solver.py
imgreg/models/logpolar/__init__.py
imgreg/models/logpolar/enums.py
imgreg/models/logpolar/params.py
imgreg/models/logpolar/solver.py
imgreg/models/radon/__init__.py
imgreg/models/radon/enums.py
imgreg/models/radon/params.py
imgreg/models/radon/solver.py
imgreg/models/validator/__init__.py
imgreg/models/validator/enums.py
imgreg/models/validator/params.py
imgreg/models/validator/solver.py
imgreg/util/__init__.py
imgreg/util/graph.py
imgreg/util/helpers.py
imgreg/util/io.py
imgreg/util/methods.py
imgreg/util/params.py
imgreg/util/solver.py
imgreg-1.0.4.dist-info/LICENSE
imgreg-1.0.4.dist-info/METADATA
imgreg-1.0.4.dist-info/WHEEL
imgreg-1.0.4.dist-info/top_level.txt
imgreg-1.0.4.dist-info/RECORD
