Metadata-Version: 2.1
Name: imgreg
Version: 1.0.4
Summary: Image registration models with extendable interfaces.
Home-page: https://gitlab.com/DigonIO/imgreg
Author: Fabian A. Preiss, Jendrik A. Potyka
Author-email: devops@digon.io, devops@digon.io
License: GPLv3
Project-URL: Documentation, https://imgreg.readthedocs.io/en/latest/
Project-URL: Source Code, https://gitlab.com/DigonIO/imgreg
Project-URL: Bug Tracker, https://gitlab.com/DigonIO/imgreg/-/issues
Keywords: image registration data analysis science
Platform: UNKNOWN
Classifier: Development Status :: 4 - Beta
Classifier: Intended Audience :: Developers
Classifier: Intended Audience :: Science/Research
Classifier: License :: OSI Approved :: GNU General Public License v3 (GPLv3)
Classifier: Programming Language :: Python :: 3.7
Classifier: Programming Language :: Python :: 3.8
Classifier: Programming Language :: Python :: 3.9
Classifier: Programming Language :: Python :: Implementation :: CPython
Classifier: Topic :: Scientific/Engineering
Classifier: Topic :: Scientific/Engineering :: Image Processing
Classifier: Topic :: Scientific/Engineering :: Visualization
Classifier: Topic :: Software Development :: Libraries
Classifier: Operating System :: Unix
Classifier: Operating System :: POSIX
Classifier: Typing :: Typed
License-File: LICENSE
Requires-Dist: numpy (==1.20.3)
Requires-Dist: scipy (==1.6.3)
Requires-Dist: scikit-image (==0.18.1)
Requires-Dist: matplotlib (==3.4.1)
Requires-Dist: typeguard (==2.12.0)
Requires-Dist: graphviz (==0.16)
Requires-Dist: Pillow (==8.2.0)
